{
  "categories": [
    "baseline-curated",
    "defi",
    "identity-reviewed",
    "otc",
    "treasury"
  ],
  "curation": {
    "gap_notes": [
      "Native chain name currently reports as Parked; multiple public directories identify SN73 as MetaHash.",
      "Official-looking docs domain docs.metahash73.com currently does not resolve from simple probes.",
      "Previously discovered GitHub source repository currently returns 404.",
      "No verified official website yet.",
      "No verified live source repository yet.",
      "No verified machine-readable OpenAPI/Swagger schema yet.",
      "No verified safe public subnet API endpoint yet.",
      "No verified SSE/event stream yet.",
      "No verified standalone static data artifact yet."
    ],
    "level": "maintainer-reviewed",
    "review_state": "maintainer-reviewed",
    "reviewed_at": "2026-06-08T14:15:00.000Z",
    "source_count": 5,
    "verified_at": "2026-06-08T14:15:00.000Z"
  },
  "dashboard_url": null,
  "docs_url": null,
  "name": "MetaHash",
  "netuid": 73,
  "notes": "Reviewed identity overlay for SN73. Native chain identity currently reports Parked, while public subnet directories identify SN73 as MetaHash. Official-looking docs and source URLs discovered from public directories currently do not resolve or return 404, so they are not promoted.",
  "schema_version": 1,
  "slug": "metahash",
  "source_repo": null,
  "status": "active",
  "surfaces": [
    {
      "auth_required": false,
      "authority": "community",
      "id": "sn-73-metahash-data-artifact",
      "kind": "data-artifact",
      "name": "MetaHash validator subnet-weights configuration",
      "notes": "Public no-auth YAML subnet-weight map used by SN73 MetaHash validators (weights.yml). Documents per-subnet weight overrides including disabling SN73 self-weight (73: 0). Pinned to immutable commit in the publicly accessible metahash repository fork; the on-chain-listed fx-integral/metahash source repo currently returns 404.",
      "provider": "metahash",
      "public_safe": true,
      "review": {
        "state": "community-submitted",
        "submitted_by": "jsdevninja"
      },
      "source_urls": [
        "https://github.com/clementblaise/metahash/blob/e1c0fac75438b62619380a0155c22a4b6cbebd34/weights.yml",
        "https://github.com/clementblaise/metahash/blob/main/docs/validator.md",
        "https://github.com/tensorplex-labs/subnet-docs/blob/main/data/73/subnet.json"
      ],
      "url": "https://raw.githubusercontent.com/clementblaise/metahash/e1c0fac75438b62619380a0155c22a4b6cbebd34/weights.yml"
    }
  ],
  "website_url": null
}
