{
  "adapter_count": 2,
  "artifact_budget_summary": {
    "fail_count": 0,
    "ok_count": 1205,
    "warn_count": 0
  },
  "artifact_budgets": [],
  "artifact_count": 22,
  "artifact_size_bytes": 3658314,
  "artifacts": [
    {
      "path": "api-index.json",
      "sha256": "05d06b56a2084e498c7f2ae450278e87fed697093adbd4675e53f60c276be188",
      "size_bytes": 73942,
      "storage_tier": "dual"
    },
    {
      "path": "changelog.json",
      "sha256": "b26e81a27716a7773c4ac6fb5e8647ae5af38270691280ffa78f51935cac3b1e",
      "size_bytes": 1480,
      "storage_tier": "dual"
    },
    {
      "path": "contracts.json",
      "sha256": "4b443c83aa9d91ffc38a5f3f76b8e103cd12b55cf04a708b16b7048eb132b24f",
      "size_bytes": 18234,
      "storage_tier": "dual"
    },
    {
      "path": "coverage.json",
      "sha256": "d378bc94568de2483ced386a71ce3c902f38f57f99495712b43ca45cab115b5e",
      "size_bytes": 982,
      "storage_tier": "dual"
    },
    {
      "path": "curation.json",
      "sha256": "32e574341cf6d9000f16ebe56e188e7e2a48dcbe509bd0f41f31dca72b7a4dde",
      "size_bytes": 156221,
      "storage_tier": "dual"
    },
    {
      "path": "evidence-ledger.json",
      "sha256": "5fd3dcefe18463119d949a5828f6b105979e5b990cbf54b3c61d524d35b3e75a",
      "size_bytes": 652425,
      "storage_tier": "dual"
    },
    {
      "path": "freshness.json",
      "sha256": "0ed01f58cbdd11cd0f77e50a74c6e3c3a8dbdf183e38df23ffcf3531ec728852",
      "size_bytes": 4323,
      "storage_tier": "dual"
    },
    {
      "path": "gaps.json",
      "sha256": "9c313800098e52539f6651772b40477201c9ca48c010629bb51f9e49a38c3e88",
      "size_bytes": 90329,
      "storage_tier": "dual"
    },
    {
      "path": "openapi.json",
      "sha256": "d57c54893b6e55b1795e3cd4babd57508518827115bfe4eb721fd75c16a2e4b5",
      "size_bytes": 322830,
      "storage_tier": "dual"
    },
    {
      "path": "profiles.json",
      "sha256": "848e0b8f8b9daa6b5dc94ac2313140c8b17a485b19731a21b22e8f1830f55169",
      "size_bytes": 342761,
      "storage_tier": "dual"
    },
    {
      "path": "providers.json",
      "sha256": "9b7cbdb2a73de1d2780d6a6a10c33f4669e0383e02008f5b37eaababbc77546f",
      "size_bytes": 27486,
      "storage_tier": "dual"
    },
    {
      "path": "review/adapter-candidates.json",
      "sha256": "acf51bff76c7193ffeeb5015ed3451e89174a9bb6b15ee91deaf6918c7fe3a87",
      "size_bytes": 26473,
      "storage_tier": "dual"
    },
    {
      "path": "review/curation.json",
      "sha256": "b896017ceb9cdd4ba09d3ce0017f5989116fdeabec198ea80c9efc230bb5b18f",
      "size_bytes": 94842,
      "storage_tier": "dual"
    },
    {
      "path": "review/enrichment-queue.json",
      "sha256": "9c6b9234929fabfef248bc99b2242286158ad0ec07255c62ee8b90e6cdfbc9b0",
      "size_bytes": 334141,
      "storage_tier": "dual"
    },
    {
      "path": "review/gap-priorities.json",
      "sha256": "69f4121865da3ff2707ff95e468148c90c58e5ac03c66de748728d03f73bab42",
      "size_bytes": 66480,
      "storage_tier": "dual"
    },
    {
      "path": "review/maintainer-decisions.json",
      "sha256": "2e57a1b5a17d8212169056572adb6ea7e55e74d0cb2b73a5ba581c597eac371f",
      "size_bytes": 1714,
      "storage_tier": "dual"
    },
    {
      "path": "review/profile-completeness.json",
      "sha256": "019b756f7d1904e2fce2702ee6c9961465a4f6bacd6b2db33a71511e23588821",
      "size_bytes": 129949,
      "storage_tier": "git"
    },
    {
      "path": "schema-drift.json",
      "sha256": "62c14d4b49c23fa3ce31cf00c0a424d25cd1f46880b3b62fe5ac73e6acb9fa22",
      "size_bytes": 9269,
      "storage_tier": "dual"
    },
    {
      "path": "schemas/index.json",
      "sha256": "46c4c740de85f0a0e562f7f87181a4c0d4ede8eae93c5517fbc61cc1fc44df9f",
      "size_bytes": 262,
      "storage_tier": "dual"
    },
    {
      "path": "search.json",
      "sha256": "a6d9cb042846c25dae38301cb0cfa60eb2772ca6783e553e18cdd5c21d04cb40",
      "size_bytes": 435931,
      "storage_tier": "dual"
    },
    {
      "path": "subnets.json",
      "sha256": "4039285de454e9961e126594a3fbbba7c7b4575df2268e430edf6727e100db15",
      "size_bytes": 120260,
      "storage_tier": "dual"
    },
    {
      "path": "surfaces.json",
      "sha256": "4643bb137b897f3f6e8b69d476ecd2df1e64e6ee97a9f3ed794aff03f8af26d3",
      "size_bytes": 747980,
      "storage_tier": "dual"
    }
  ],
  "candidate_count": 1891,
  "contract_version": "2026-06-06.1",
  "coverage": {
    "application_subnet_count": 128,
    "candidate_count": 1891,
    "candidate_subnet_count": 129,
    "chain_subnet_count": 129,
    "curated_overlay_count": 129,
    "curation_level_counts": {
      "adapter-backed": 2,
      "machine-verified": 67,
      "maintainer-reviewed": 60
    },
    "generated_at": "1970-01-01T00:00:00.000Z",
    "manifested_count": 0,
    "native_only_count": 0,
    "native_only_with_candidates": 0,
    "native_only_without_candidates": 0,
    "native_snapshot_captured_at": "2026-06-07T21:51:54Z",
    "network": "finney",
    "probed_count": 129,
    "probed_surface_count": 767,
    "root_subnet_count": 1,
    "schema_version": 1,
    "source": {
      "candidates": "registry/candidates",
      "native": {
        "kind": "bittensor-sdk",
        "method": "SubtensorApi.metagraphs.get_all_metagraphs_info(all_mechanisms=True)",
        "package": "bittensor",
        "rpc_family": "subnetInfo",
        "version": "10.4.0"
      },
      "overlays": "registry/subnets"
    },
    "surface_count": 771
  },
  "endpoint_count": 771,
  "full_artifact_count": 1205,
  "full_artifact_size_bytes": 39798701,
  "generated_at": "1970-01-01T00:00:00.000Z",
  "profile_count": 129,
  "provider_count": 67,
  "public_contract": {
    "url": "/metagraph/contracts.json",
    "version": "2026-06-06.1"
  },
  "schema_version": 1,
  "storage_tier_counts": {
    "dual": 21,
    "git": 1,
    "r2": 1183
  },
  "storage_tier_size_bytes": {
    "dual": 3528365,
    "git": 129949,
    "r2": 36140387
  },
  "subnet_count": 129,
  "surface_count": 771
}
