{
  "artifacts": {
    "added": [],
    "modified": [
      {
        "hash": "88a695ea76257b3eef1bada7ddab089ba116921d013a4f6e7baeb88c79a31475",
        "path": "coverage.json"
      },
      {
        "hash": "81b9aec2471f3a5682cea941b3e183b75a447c6c2e13401229e8d1e026b8d95a",
        "path": "review/profile-completeness.json"
      },
      {
        "hash": "aeaed9ad3734d48045cc869e4809849b3e1ca2bc35702c6cc5d78873b735ec98",
        "path": "subnets.json"
      }
    ],
    "removed": []
  },
  "contract_version": "2026-06-06.1",
  "generated_at": "1970-01-01T00:00:00.000Z",
  "notes": [
    "This changelog compares the latest generated artifacts against the previous checked-in public artifact state before the build.",
    "Long-term historical runs are expected to live in R2 under versioned prefixes."
  ],
  "schema_version": 1,
  "source": "generated-artifact-diff",
  "subnets": {
    "added": [],
    "removed": [],
    "renamed": []
  },
  "summary": {
    "artifact_added_count": 0,
    "artifact_modified_count": 3,
    "artifact_removed_count": 0,
    "coverage_delta": {
      "candidate_count": {
        "after": 2025,
        "before": 2024,
        "delta": 1
      },
      "curated_overlay_count": {
        "after": 129,
        "before": 129,
        "delta": 0
      },
      "native_only_count": {
        "after": 0,
        "before": 0,
        "delta": 0
      },
      "provider_count": null,
      "surface_count": {
        "after": 1140,
        "before": 1140,
        "delta": 0
      }
    },
    "netuid_added_count": 0,
    "netuid_removed_count": 0,
    "netuid_renamed_count": 0
  }
}
